{
  "project_info": {
    "project_number": "779811271303",
    "project_id": "warm-now-381709",
    "storage_bucket": "warm-now-381709.appspot.com"
  },
  "client": [
    {
      "client_info": {
        "mobilesdk_app_id": "1:779811271303:android:4c18ee4106fe6b73b53e22",
        "android_client_info": {
          "package_name": "ru.technosopher.attendancelogappstudents"
        }
      },
      "oauth_client": [],
      "api_key": [
        {
          "current_key": "AIzaSyBe_3-ocBO4L8BUXl_RHG8O6r6EhNl45xc"
        }
      ],
      "services": {
        "appinvite_service": {
          "other_platform_oauth_client": []
        }
      }
    },
    {
      "client_info": {
        "mobilesdk_app_id": "1:779811271303:android:a9d989d925fde584b53e22",
        "android_client_info": {
          "package_name": "ru.technosopher.firebasetest"
        }
      },
      "oauth_client": [],
      "api_key": [
        {
          "current_key": "AIzaSyBe_3-ocBO4L8BUXl_RHG8O6r6EhNl45xc"
        }
      ],
      "services": {
        "appinvite_service": {
          "other_platform_oauth_client": []
        }
      }
    }
  ],
  "configuration_version": "1"
}